geci_data/__init__.py
geci_data/api.py
geci_data-0.0.1.dist-info/LICENSE
geci_data-0.0.1.dist-info/WHEEL
geci_data-0.0.1.dist-info/METADATA
geci_data-0.0.1.dist-info/RECORD
