Metadata-Version: 2.1
Name: geci_data
Version: 0.0.1
Summary: A template Python module
Home-page: https://github.com/IslasGECI/geci_data
Author: Ciencia de Datos • GECI
Author-email: ciencia.datos@islas.org.mx
Requires-Python: >=3.9
Classifier: License :: OSI Approved :: GNU General Public License v3 or later (GPLv3+)
Requires-Dist: fastapi
Requires-Dist: httpx
